Metadata-Version: 1.1
Name: datacoco-core
Version: 0.1.1
Summary: Data common code for core features by Equinox
Home-page: https://github.com/equinoxfitness/datacoco-core
Author: Equinox Fitness
Author-email: UNKNOWN
License: MIT
Keywords: helper,config,logging,common
Platform: UNKNOWN
Classifier: Development Status :: 5 - Production/Stable
Classifier: Intended Audience :: Developers
Classifier: Natural Language :: English
Classifier: License :: OSI Approved :: MIT License
Classifier: Programming Language :: Python :: 3.6
